[
    {
        "platform": "windows",
        "arch": "i386",
        "version": "0.8.1",
        "browser_url": "https://github.com/moonlight-stream/moonlight-qt/releases"
    },
    {
        "platform": "windows",
        "arch": "x86_64",
        "version": "0.8.1",
        "browser_url": "https://github.com/moonlight-stream/moonlight-qt/releases"
    },
    {
        "platform": "osx",
        "arch": "x86_64",
        "version": "0.8.1",
        "browser_url": "https://github.com/moonlight-stream/moonlight-qt/releases"
    }
]